wapipelines/__init__.py
wapipelines/admin.py
wapipelines/apps.py
wapipelines/forms.py
wapipelines/models.py
wapipelines/tasks.py
wapipelines/urls.py
wapipelines/views.py
wapipelines/api/__init__.py
wapipelines/api/serializers.py
wapipelines/api/views.py
wapipelines/api/tests/__init__.py
wapipelines/api/tests/test_views.py
wapipelines/migrations/0001_initial.py
wapipelines/migrations/__init__.py
wapipelines/templatetags/__init__.py
wapipelines/templatetags/wapipeline_tags.py
wapipelines/tests/__init__.py
wapipelines/tests/test_models.py
wapipelines-0.2.0.dist-info/DESCRIPTION.rst
wapipelines-0.2.0.dist-info/METADATA
wapipelines-0.2.0.dist-info/RECORD
wapipelines-0.2.0.dist-info/WHEEL
wapipelines-0.2.0.dist-info/metadata.json
wapipelines-0.2.0.dist-info/top_level.txt
