Metadata-Version: 2.0
Name: wapipelines
Version: 0.2.0
Summary: WA Pipelines
Home-page: https://github.com/praekeltfoundation/wa-pipelines
Author: Simon de Haan
Author-email: simon@praekelt.org
License: UNKNOWN
Keywords: wa-pipelines
Platform: UNKNOWN
Classifier: Intended Audience :: Developers
Classifier: Natural Language :: English
Classifier: Programming Language :: Python :: 2.7
Classifier: Programming Language :: Python :: 3.6
Requires-Dist: Django (<2.0,>=1.11)
Requires-Dist: social-auth-app-django (<2.0,>=1.1.0)
Requires-Dist: djangorestframework (<4.0,>=3.6.4)
Requires-Dist: psycopg2 (<3.0,>=2.7.1)
Requires-Dist: networkx (<2.0,>=1.11)
Requires-Dist: pydotplus (<3.0,>=2.0.2)
Requires-Dist: celery (<5.0,>=4.0.2)
Requires-Dist: django-bower (<6.0,>=5.2.0)
Requires-Dist: django-digg-paginator (<1.0,>=0.1.3)
Requires-Dist: dj-database-url (<1.0,>=0.4.2)
Requires-Dist: django-getenv (<2.0,>=1.3.1)
Requires-Dist: raven (<7.0,>=6.1.0)
Requires-Dist: whitenoise (<4.0,>=3.3.0)
Requires-Dist: django-dotenv (<2.0,>=1.4.1)
Requires-Dist: coreapi (<3.0,>=2.3.0)
Provides-Extra: dev
Requires-Dist: flake8; extra == 'dev'
Requires-Dist: pytest; extra == 'dev'
Requires-Dist: pytest-xdist; extra == 'dev'
Requires-Dist: pytest-cov; extra == 'dev'
Requires-Dist: pytest-django; extra == 'dev'
Requires-Dist: mock; extra == 'dev'
Requires-Dist: responses; extra == 'dev'
Requires-Dist: dj-database-url; extra == 'dev'
Requires-Dist: twine; extra == 'dev'
